{
  "parent": "minecraft:recipes/root",
  "rewards": {
    "recipes": [
      "enchanted:fume_filter"
    ]
  },
  "criteria": {
    "has_attuned_stone": {
      "trigger": "minecraft:inventory_changed",
      "conditions": {
        "items": [
          {
            "items": [
              "enchanted:attuned_stone"
            ]
          }
        ]
      }
    },
    "has_the_recipe": {
      "trigger": "minecraft:recipe_unlocked",
      "conditions": {
        "recipe": "enchanted:fume_filter"
      }
    }
  },
  "requirements": [
    [
      "has_attuned_stone",
      "has_the_recipe"
    ]
  ]
}